{
    "routes" :{
        "controllers" :{
        },
        "sockets" :{
            "index" :{
                "indexAction" :{
                    "path":"index/index"
                }
            },
            "player" :{
            },
            "game" :{
                "addGameAction" :{
                    "path":"game/add-game"
                },
                "getGameAction" :{
                    "path":"game/get-game"
                },
                "getHistoryAction" :{
                    "path":"game/get-games"
                },
                "pushRoundAction" :{
                    "path":"game/push-round"
                }
            },
            "user" :{
                "isLoggedAction" :{
                    "path":"user/is-logged"
                },
                "submitLoginAction" :{
                    "path":"user/submit-login"
                },
                "getUserAction" :{
                    "path":"user/get-user"
                }
            }
        }
    }
}